bouquin/__init__.py
bouquin/__main__.py
bouquin/bug_report_dialog.py
bouquin/code_block_editor_dialog.py
bouquin/code_highlighter.py
bouquin/db.py
bouquin/document_utils.py
bouquin/documents.py
bouquin/find_bar.py
bouquin/flow_layout.py
bouquin/fonts/DejaVu.license
bouquin/fonts/DejaVuSans.ttf
bouquin/fonts/Noto.license
bouquin/fonts/NotoSansSymbols2-Regular.ttf
bouquin/history_dialog.py
bouquin/icons/bouquin.svg
bouquin/invoices.py
bouquin/key_prompt.py
bouquin/keys/mig5.asc
bouquin/locales/en.json
bouquin/locales/fr.json
bouquin/locales/it.json
bouquin/lock_overlay.py
bouquin/main.py
bouquin/main_window.py
bouquin/markdown_editor.py
bouquin/markdown_highlighter.py
bouquin/pomodoro_timer.py
bouquin/reminders.py
bouquin/save_dialog.py
bouquin/search.py
bouquin/settings.py
bouquin/settings_dialog.py
bouquin/statistics_dialog.py
bouquin/strings.py
bouquin/tag_browser.py
bouquin/tags_widget.py
bouquin/theme.py
bouquin/time_log.py
bouquin/toolbar.py
bouquin/version_check.py
bouquin-0.8.3.dist-info/LICENSE
bouquin-0.8.3.dist-info/METADATA
bouquin-0.8.3.dist-info/WHEEL
bouquin-0.8.3.dist-info/entry_points.txt
bouquin-0.8.3.dist-info/RECORD
