Metadata-Version: 2.1
Name: bouquin
Version: 0.8.3
Summary: Bouquin is a simple, opinionated notebook application written in Python, PyQt and SQLCipher.
Home-page: https://git.mig5.net/mig5/bouquin
License: GPL-3.0-or-later
Author: Miguel Jacq
Author-email: mig@mig5.net
Requires-Python: >=3.10,<3.14
Classifier: License :: OSI Approved :: GNU General Public License v3 or later (GPLv3+)
Classifier: Programming Language :: Python :: 3
Classifier: Programming Language :: Python :: 3.10
Classifier: Programming Language :: Python :: 3.11
Classifier: Programming Language :: Python :: 3.12
Requires-Dist: bouquin-sqlcipher4 (>=4.12.0,<5.0.0)
Requires-Dist: markdown (>=3.7,<4.0)
Requires-Dist: pyside6 (>=6.8.1,<7.0.0)
Requires-Dist: requests (>=2.32.3,<3.0.0)
Project-URL: Repository, https://git.mig5.net/mig5/bouquin
